{
	"title": "new json layout v2",
	"description": "",
	"body": [
		{
			"section": {
				"type": "heading",
				"text": "Head first into the Signs EP"
			}
		},
		{
			"section": {
				"type": "paragraph",
				"text": "Head first into the Signs EP"
			}
		},
		{
			"section": {
				"type": "img",
				"img": "blah blah blah"
			}
		},
		{
			"section": {
				"type": "question",
				"text": "question"
			}
		},
		{
			"section": {
				"type": "answer",
				"text": "answer"
			}
		},
		{
			"section": {
				"type": "bulletList",
				"list": [
					"Blah",
					"Blah",
					"Blah"
				]
			}
		},
		{
			"section": {
				"type": "numberedList",
				"list": [
					"Blah",
					"Blah",
					"Blah"
				]
			}
		},
		{
			"section": {
				"type": "soundcloud",
				"id": "313636877",
				"text": "Aagentah - Babylon"
			}
		},
		{
			"section": {
				"type": "youtube",
				"url": "www.youtube.com/blah"
			}
		},
		{
			"section": {
				"type": "link",
				"text": "blah",
				"url": "ww/blah"
			}
		}
	],
	"created": {
		"date": "",
		"author": ""
	}
}
